[
    {
        "id": "US/NonFarmPayrolls/MoM",
        "providers": [
            {
                "name": "Investing.com",
                "parameters": {
                    "uri": "https://www.investing.com/economic-calendar/nonfarm-payrolls-227"
                }
            }
        ]
    },
    {
        "id": "US/UnemploymentRate/MoM",
        "providers": [
            {
                "name": "Investing.com",
                "parameters": {
                    "uri": "https://www.investing.com/economic-calendar/unemployment-rate-300"
                }
            }
        ]
    },
    {
        "id": "US/InterestRate",
        "providers": [
            {
                "name": "Investing.com",
                "parameters": {
                    "uri": "https://www.investing.com/economic-calendar/interest-rate-decision-168"
                }
            }
        ]
    },
    {
        "id": "US/CPI/YoY",
        "providers": [
            {
                "name": "Investing.com",
                "parameters": {
                    "uri": "https://www.investing.com/economic-calendar/cpi-733"
                }
            }
        ]
    },
    {
        "id": "US/CoreCPI/MoM",
        "providers": [
            {
                "name": "Investing.com",
                "parameters": {
                    "uri": "https://www.investing.com/economic-calendar/core-cpi-56"
                }
            }
        ]
    },
    {
        "id": "US/CoreCPI/YoY",
        "providers": [
            {
                "name": "Investing.com",
                "parameters": {
                    "uri": "https://www.investing.com/economic-calendar/core-cpi-736"
                }
            }
        ]
    },
    {
        "id": "US/CrudeOilInventories/WoW",
        "providers": [
            {
                "name": "Investing.com",
                "parameters": {
                    "uri": "https://www.investing.com/economic-calendar/eia-crude-oil-inventories-75"
                }
            }
        ]
    },
    {
        "id": "Eurozone/CPI/YoY",
        "providers": [
            {
                "name": "Investing.com",
                "parameters": {
                    "uri": "https://www.investing.com/economic-calendar/cpi-68"
                }
            }
        ]
    },
    {
        "id": "Eurozone/InterestRate",
        "providers": [
            {
                "name": "Investing.com",
                "parameters": {
                    "uri": "https://www.investing.com/economic-calendar/interest-rate-decision-164"
                }
            }
        ]
    },
    {
        "id": "Italy/CPI/YoY",
        "providers": [
            {
                "name": "Investing.com",
                "parameters": {
                    "uri": "https://www.investing.com/economic-calendar/italian-cpi-748"
                }
            }
        ]
    },
    {
        "id": "Canada/InterestRate",
        "providers": [
            {
                "name": "Investing.com",
                "parameters": {
                    "uri": "https://www.investing.com/economic-calendar/interest-rate-decision-166"
                }
            }
        ]
    },
    {
        "id": "Japan/CPI/YoY",
        "providers": [
            {
                "name": "Investing.com",
                "parameters": {
                    "uri": "https://www.investing.com/economic-calendar/national-cpi-992"
                }
            }
        ]
    },
    {
        "id": "Germany/CPI/YoY",
        "providers": [
            {
                "name": "Investing.com",
                "parameters": {
                    "uri": "https://www.investing.com/economic-calendar/german-cpi-737"
                }
            }
        ]
    }
]
